.DS_Store
geepal/.DS_Store
geepal/__init__.py
geepal/cals.py
geepal/dfsort.py
geepal/get_events.py
geepal/relrange_class.py
geepal/rescuetime.py
geepal/tmp.py
geepal-0.2.2.data/scripts/invoice.py
geepal-0.2.2.dist-info/DESCRIPTION.rst
geepal-0.2.2.dist-info/METADATA
geepal-0.2.2.dist-info/RECORD
geepal-0.2.2.dist-info/WHEEL
geepal-0.2.2.dist-info/metadata.json
geepal-0.2.2.dist-info/top_level.txt
