Metadata-Version: 2.0
Name: geepal
Version: 0.2.2
Summary: From Google Calendar to dataframes
Home-page: https://github.com/eayoungs/Gcal
Author: Eric Allen Youngson
Author-email: eayoungs@gmail.com
License: LICENSE.txt
Download-URL: https://github.com/eayoungs/Gcal/archive/master.zip
Keywords: time,tracking,calendar,dataframe
Platform: UNKNOWN
Requires-Dist: google-api-python-client (>=1.6.1)
Requires-Dist: oauth2client (>=4.0.0)
Requires-Dist: httplib2 (>=0.9.2)
Requires-Dist: iso8601 (>=0.1.11)
Requires-Dist: matplotlib (>=2.0.0)
Requires-Dist: pandas (>=0.19.2)
Requires-Dist: python-dateutil (>=2.5.3)
Requires-Dist: pytz (>=2016.4)
Requires-Dist: tzlocal (>=1.3)
Requires-Dist: parsedatetime (>=2.1)
Requires-Dist: jupyter (>=1.0.0)
Requires-Dist: pytest (>=3.0.6)
Requires-Dist: regex (>=2016.7.21)
Requires-Dist: pyinvoice (>=0.1.7)
